ali/__init__.py
ali/cli.py
ali/commands/__init__.py
ali/commands/configure.py
ali/commands/cr.py
ali/commands/kms.py
ali/commands/params.py
ali/commands/ros.py
ali/commands/crypto/__init__.py
ali/commands/crypto/oss.py
ali/commands/mns/__init__.py
ali/commands/mns/client.py
ali/commands/mns/queue.py
ali/commands/mns/util.py
ali/commands/mns/requests/__init__.py
ali/commands/mns/requests/base_request.py
ali/commands/mns/requests/queue.py
ali/helpers/__init__.py
ali/helpers/auth.py
ali/helpers/oss.py
ali/helpers/output.py
ali/helpers/template.py
ali_cli-0.7.3.dist-info/METADATA
ali_cli-0.7.3.dist-info/WHEEL
ali_cli-0.7.3.dist-info/entry_points.txt
ali_cli-0.7.3.dist-info/top_level.txt
ali_cli-0.7.3.dist-info/RECORD
