Metadata-Version: 2.1
Name: ali-cli
Version: 0.7.3
Summary: Wraps the Alibaba Cloud SDK to make complicated tasks a lot simpler.
Home-page: https://github.com/leonrodenburg/ali-cli
Author: Léon Rodenburg
Author-email: lrodenburg@xebia.com
License: UNKNOWN
Keywords: alibaba cloud aliyun cli
Platform: UNKNOWN
Requires-Python: >=3.6
Requires-Dist: click (>=7.0)
Requires-Dist: colorama (>=0.4.1)
Requires-Dist: pygments (>=2.4.2)
Requires-Dist: ruamel.yaml (>=0.16.5)
Requires-Dist: xmltodict (>=0.12.0)
Requires-Dist: requests (>=2.22.0)
Requires-Dist: urllib3 (>=1.25.3)
Requires-Dist: cryptography (>=2.7)
Requires-Dist: humanize (>=0.5.1)
Requires-Dist: aliyun-python-sdk-core (>=2.13)
Requires-Dist: aliyun-python-sdk-ros (>=2.2.8)
Requires-Dist: aliyun-python-sdk-kms (>=2.5.0)
Requires-Dist: aliyun-python-sdk-sts (>=3.0.1)
Requires-Dist: aliyun-python-sdk-cr (>=3.0.1)
Requires-Dist: oss2 (>=2.8.0)
